[
  {
    "No.": "#0172",
    "Pic": "https://www.serebii.net/pokemongo/pokemon/172.png",
    "Name": "Pichu",
    "Type": {
      "Typo1": "electric"
    },
    "Egg Distance": "2km",
    "Max CP At Hatch": "270",
    "Shiny": "si"
  },
  {
    "No.": "#0173",
    "Pic": "https://www.serebii.net/pokemongo/pokemon/173.png",
    "Name": "Cleffa",
    "Type": {
      "Typo1": "fairy"
    },
    "Egg Distance": "2km",
    "Max CP At Hatch": "383",
    "Shiny": "si"
  },
  {
    "No.": "#0174",
    "Pic": "https://www.serebii.net/pokemongo/pokemon/174.png",
    "Name": "Igglybuff",
    "Type": {
      "Typo1": "normal",
      "Typo2": "fairy"
    },
    "Egg Distance": "2km",
    "Max CP At Hatch": "306",
    "Shiny": "si"
  },
  {
    "No.": "#0175",
    "Pic": "https://www.serebii.net/pokemongo/pokemon/175.png",
    "Name": "Togepi",
    "Type": {
      "Typo1": "fairy"
    },
    "Egg Distance": "2km",
    "Max CP At Hatch": "375",
    "Shiny": "si"
  },
  {
    "No.": "#0236",
    "Pic": "https://www.serebii.net/pokemongo/pokemon/236.png",
    "Name": "Tyrogue",
    "Type": {
      "Typo1": "fighting"
    },
    "Egg Distance": "2km",
    "Max CP At Hatch": "281",
    "Shiny": "si"
  },
  {
    "No.": "#0360",
    "Pic": "https://www.serebii.net/pokemongo/pokemon/360.png",
    "Name": "Wynaut",
    "Type": {
      "Typo1": "psychic"
    },
    "Egg Distance": "2km",
    "Max CP At Hatch": "305",
    "Shiny": "si"
  },
  {
    "No.": "#0636",
    "Pic": "https://www.serebii.net/pokemongo/pokemon/636.png",
    "Name": "Larvesta",
    "Type": {
      "Typo1": "bug",
      "Typo2": "fire"
    },
    "Egg Distance": "2km",
    "Max CP At Hatch": "855",
    "Shiny": "si"
  },
  {
    "No.": "#0302",
    "Pic": "https://www.serebii.net/pokemongo/pokemon/302.png",
    "Name": "Sableye",
    "Type": {
      "Typo1": "dark",
      "Typo2": "ghost"
    },
    "Egg Distance": "5km",
    "Max CP At Hatch": "843",
    "Shiny": "si"
  },
  {
    "No.": "#0582",
    "Pic": "https://www.serebii.net/pokemongo/pokemon/582.png",
    "Name": "Vanillite",
    "Type": {
      "Typo1": "ice"
    },
    "Egg Distance": "5km",
    "Max CP At Hatch": "590",
    "Shiny": "si"
  },
  {
    "No.": "#0636",
    "Pic": "https://www.serebii.net/pokemongo/pokemon/636.png",
    "Name": "Larvesta",
    "Type": {
      "Typo1": "bug",
      "Typo2": "fire"
    },
    "Egg Distance": "5km",
    "Max CP At Hatch": "855",
    "Shiny": "si"
  },
  {
    "No.": "#0742",
    "Pic": "https://www.serebii.net/pokemongo/pokemon/742.png",
    "Name": "Cutiefly",
    "Type": {
      "Typo1": "bug",
      "Typo2": "fairy"
    },
    "Egg Distance": "5km",
    "Max CP At Hatch": "507",
    "Shiny": "si"
  },
  {
    "No.": "#0775",
    "Pic": "https://www.serebii.net/pokemongo/pokemon/775.png",
    "Name": "Komala",
    "Type": {
      "Typo1": "normal"
    },
    "Egg Distance": "5km",
    "Max CP At Hatch": "1475",
    "Shiny": "si"
  },
  {
    "No.": "#0810",
    "Pic": "https://www.serebii.net/pokemongo/pokemon/810.png",
    "Name": "Grookey",
    "Type": {
      "Typo1": "grass"
    },
    "Egg Distance": "5km",
    "Max CP At Hatch": "620",
    "Shiny": "no"
  },
  {
    "No.": "#0813",
    "Pic": "https://www.serebii.net/pokemongo/pokemon/813.png",
    "Name": "Scorbunny",
    "Type": {
      "Typo1": "fire"
    },
    "Egg Distance": "5km",
    "Max CP At Hatch": "627",
    "Shiny": "no"
  },
  {
    "No.": "#0816",
    "Pic": "https://www.serebii.net/pokemongo/pokemon/816.png",
    "Name": "Sobble",
    "Type": {
      "Typo1": "water"
    },
    "Egg Distance": "5km",
    "Max CP At Hatch": "627",
    "Shiny": "no"
  },
  {
    "No.": "#0027",
    "Pic": "https://www.serebii.net/pokemongo/pokemon/027-a.png",
    "Name": "Sandshrew",
    "Type": {
      "Typo1": "ice",
      "Typo2": "steel"
    },
    "Egg Distance": "7km",
    "Max CP At Hatch": "739",
    "Shiny": "si"
  },
  {
    "No.": "#0037",
    "Pic": "https://www.serebii.net/pokemongo/pokemon/037-a.png",
    "Name": "Vulpix",
    "Type": {
      "Typo1": "ice"
    },
    "Egg Distance": "7km",
    "Max CP At Hatch": "504",
    "Shiny": "si"
  },
  {
    "No.": "#0052",
    "Pic": "https://www.serebii.net/pokemongo/pokemon/052-a.png",
    "Name": "Meowth",
    "Type": {
      "Typo1": "dark"
    },
    "Egg Distance": "7km",
    "Max CP At Hatch": "455",
    "Shiny": "si"
  },
  {
    "No.": "#0052",
    "Pic": "https://www.serebii.net/pokemongo/pokemon/052-g.png",
    "Name": "Meowth",
    "Type": {
      "Typo1": "steel"
    },
    "Egg Distance": "7km",
    "Max CP At Hatch": "591",
    "Shiny": "si"
  },
  {
    "No.": "#0074",
    "Pic": "https://www.serebii.net/pokemongo/pokemon/074-a.png",
    "Name": "Geodude",
    "Type": {
      "Typo1": "rock",
      "Typo2": "electric"
    },
    "Egg Distance": "7km",
    "Max CP At Hatch": "739",
    "Shiny": "si"
  },
  {
    "No.": "#0077",
    "Pic": "https://www.serebii.net/pokemongo/pokemon/077-g.png",
    "Name": "Ponyta",
    "Type": {
      "Typo1": "psychic"
    },
    "Egg Distance": "7km",
    "Max CP At Hatch": "969",
    "Shiny": "si"
  },
  {
    "No.": "#0079",
    "Pic": "https://www.serebii.net/pokemongo/pokemon/079-g.png",
    "Name": "Slowpoke",
    "Type": {
      "Typo1": "psychic"
    },
    "Egg Distance": "7km",
    "Max CP At Hatch": "700",
    "Shiny": "si"
  },
  {
    "No.": "#0083",
    "Pic": "https://www.serebii.net/pokemongo/pokemon/083-g.png",
    "Name": "Farfetch'd",
    "Type": {
      "Typo1": "fighting"
    },
    "Egg Distance": "7km",
    "Max CP At Hatch": "956",
    "Shiny": "si"
  },
  {
    "No.": "#0088",
    "Pic": "https://www.serebii.net/pokemongo/pokemon/088-a.png",
    "Name": "Grimer",
    "Type": {
      "Typo1": "poison",
      "Typo2": "dark"
    },
    "Egg Distance": "7km",
    "Max CP At Hatch": "785",
    "Shiny": "si"
  },
  {
    "No.": "#0194",
    "Pic": "https://www.serebii.net/pokemongo/pokemon/194-p.png",
    "Name": "Wooper",
    "Type": {
      "Typo1": "poison",
      "Typo2": "ground"
    },
    "Egg Distance": "7km",
    "Max CP At Hatch": "366",
    "Shiny": "si"
  },
  {
    "No.": "#0263",
    "Pic": "https://www.serebii.net/pokemongo/pokemon/263-g.png",
    "Name": "Zigzagoon",
    "Type": {
      "Typo1": "dark",
      "Typo2": "normal"
    },
    "Egg Distance": "7km",
    "Max CP At Hatch": "290",
    "Shiny": "si"
  },
  {
    "No.": "#0554",
    "Pic": "https://www.serebii.net/pokemongo/pokemon/554-g.png",
    "Name": "Darumaka",
    "Type": {
      "Typo1": "ice"
    },
    "Egg Distance": "7km",
    "Max CP At Hatch": "824",
    "Shiny": "si"
  },
  {
    "No.": "#0618",
    "Pic": "https://www.serebii.net/pokemongo/pokemon/618-g.png",
    "Name": "Stunfisk",
    "Type": {
      "Typo1": "ground",
      "Typo2": "steel"
    },
    "Egg Distance": "7km",
    "Max CP At Hatch": "1235",
    "Shiny": "si"
  },
  {
    "No.": "#0621",
    "Pic": "https://www.serebii.net/pokemongo/pokemon/621.png",
    "Name": "Druddigon",
    "Type": {
      "Typo1": "dragon"
    },
    "Egg Distance": "10km",
    "Max CP At Hatch": "1561",
    "Shiny": "si"
  },
  {
    "No.": "#0636",
    "Pic": "https://www.serebii.net/pokemongo/pokemon/636.png",
    "Name": "Larvesta",
    "Type": {
      "Typo1": "bug",
      "Typo2": "fire"
    },
    "Egg Distance": "10km",
    "Max CP At Hatch": "855",
    "Shiny": "si"
  },
  {
    "No.": "#0703",
    "Pic": "https://www.serebii.net/pokemongo/pokemon/703.png",
    "Name": "Carbink",
    "Type": {
      "Typo1": "rock",
      "Typo2": "fairy"
    },
    "Egg Distance": "10km",
    "Max CP At Hatch": "838",
    "Shiny": "no"
  },
  {
    "No.": "#0704",
    "Pic": "https://www.serebii.net/pokemongo/pokemon/704.png",
    "Name": "Goomy",
    "Type": {
      "Typo1": "dragon"
    },
    "Egg Distance": "10km",
    "Max CP At Hatch": "557",
    "Shiny": "si"
  },
  {
    "No.": "#0885",
    "Pic": "https://www.serebii.net/pokemongo/pokemon/885.png",
    "Name": "Dreepy",
    "Type": {
      "Typo1": "dragon",
      "Typo2": "ghost"
    },
    "Egg Distance": "10km",
    "Max CP At Hatch": "438",
    "Shiny": "no"
  },
  {
    "No.": "#0935",
    "Pic": "https://www.serebii.net/pokemongo/pokemon/935.png",
    "Name": "Charcadet",
    "Type": {
      "Typo1": "fire"
    },
    "Egg Distance": "10km",
    "Max CP At Hatch": "418",
    "Shiny": "no"
  },
  {
    "No.": "#0996",
    "Pic": "https://www.serebii.net/pokemongo/pokemon/996.png",
    "Name": "Frigibax",
    "Type": {
      "Typo1": "dragon",
      "Typo2": "ice"
    },
    "Egg Distance": "10km",
    "Max CP At Hatch": "713",
    "Shiny": "no"
  },
  {
    "No.": "#0246",
    "Pic": "https://www.serebii.net/pokemongo/pokemon/246.png",
    "Name": "Larvitar",
    "Type": {
      "Typo1": "rock",
      "Typo2": "ground"
    },
    "Egg Distance": "12km",
    "Max CP At Hatch": "594",
    "Shiny": "si"
  },
  {
    "No.": "#0551",
    "Pic": "https://www.serebii.net/pokemongo/pokemon/551.png",
    "Name": "Sandile",
    "Type": {
      "Typo1": "ground",
      "Typo2": "dark"
    },
    "Egg Distance": "12km",
    "Max CP At Hatch": "592",
    "Shiny": "si"
  },
  {
    "No.": "#0624",
    "Pic": "https://www.serebii.net/pokemongo/pokemon/624.png",
    "Name": "Pawniard",
    "Type": {
      "Typo1": "dark",
      "Typo2": "steel"
    },
    "Egg Distance": "12km",
    "Max CP At Hatch": "819",
    "Shiny": "si"
  },
  {
    "No.": "#0629",
    "Pic": "https://www.serebii.net/pokemongo/pokemon/629.png",
    "Name": "Vullaby",
    "Type": {
      "Typo1": "dark",
      "Typo2": "flying"
    },
    "Egg Distance": "12km",
    "Max CP At Hatch": "726",
    "Shiny": "si"
  },
  {
    "No.": "#0633",
    "Pic": "https://www.serebii.net/pokemongo/pokemon/633.png",
    "Name": "Deino",
    "Type": {
      "Typo1": "dark",
      "Typo2": "dragon"
    },
    "Egg Distance": "12km",
    "Max CP At Hatch": "606",
    "Shiny": "si"
  },
  {
    "No.": "#0674",
    "Pic": "https://www.serebii.net/pokemongo/pokemon/674.png",
    "Name": "Pancham",
    "Type": {
      "Typo1": "fighting"
    },
    "Egg Distance": "12km",
    "Max CP At Hatch": "850",
    "Shiny": "si"
  },
  {
    "No.": "#0757",
    "Pic": "https://www.serebii.net/pokemongo/pokemon/757.png",
    "Name": "Salandit",
    "Type": {
      "Typo1": "poison",
      "Typo2": "fire"
    },
    "Egg Distance": "12km",
    "Max CP At Hatch": "641",
    "Shiny": "no"
  },
  {
    "No.": "#0965",
    "Pic": "https://www.serebii.net/pokemongo/pokemon/965.png",
    "Name": "Varoom",
    "Type": {
      "Typo1": "steel",
      "Typo2": "poison"
    },
    "Egg Distance": "12km",
    "Max CP At Hatch": "650",
    "Shiny": "no"
  },
  {
    "No.": "#0433",
    "Pic": "https://www.serebii.net/pokemongo/pokemon/433.png",
    "Name": "Chingling",
    "Type": {
      "Typo1": "psychic"
    },
    "Egg Distance": "Adventure Sync - 5km",
    "Max CP At Hatch": "574",
    "Shiny": "si"
  },
  {
    "No.": "#0448",
    "Pic": "https://www.serebii.net/pokemongo/pokemon/448.png",
    "Name": "Lucario",
    "Type": {
      "Typo1": "fighting",
      "Typo2": "steel"
    },
    "Egg Distance": "Adventure Sync - 5km",
    "Max CP At Hatch": "1544",
    "Shiny": "si"
  },
  {
    "No.": "#0696",
    "Pic": "https://www.serebii.net/pokemongo/pokemon/696.png",
    "Name": "Tyrunt",
    "Type": {
      "Typo1": "rock",
      "Typo2": "dragon"
    },
    "Egg Distance": "Adventure Sync - 5km",
    "Max CP At Hatch": "934",
    "Shiny": "si"
  },
  {
    "No.": "#0698",
    "Pic": "https://www.serebii.net/pokemongo/pokemon/698.png",
    "Name": "Amaura",
    "Type": {
      "Typo1": "rock",
      "Typo2": "ice"
    },
    "Egg Distance": "Adventure Sync - 5km",
    "Max CP At Hatch": "779",
    "Shiny": "si"
  },
  {
    "No.": "#0708",
    "Pic": "https://www.serebii.net/pokemongo/pokemon/708.png",
    "Name": "Phantump",
    "Type": {
      "Typo1": "ghost",
      "Typo2": "grass"
    },
    "Egg Distance": "Adventure Sync - 5km",
    "Max CP At Hatch": "642",
    "Shiny": "si"
  },
  {
    "No.": "#0147",
    "Pic": "https://www.serebii.net/pokemongo/pokemon/147.png",
    "Name": "Dratini",
    "Type": {
      "Typo1": "dragon"
    },
    "Egg Distance": "Adventure Sync - 10km",
    "Max CP At Hatch": "574",
    "Shiny": "si"
  },
  {
    "No.": "#0744",
    "Pic": "https://www.serebii.net/pokemongo/pokemon/744.png",
    "Name": "Rockruff",
    "Type": {
      "Typo1": "rock"
    },
    "Egg Distance": "Adventure Sync - 10km",
    "Max CP At Hatch": "543",
    "Shiny": "si"
  },
  {
    "No.": "#0780",
    "Pic": "https://www.serebii.net/pokemongo/pokemon/780.png",
    "Name": "Drampa",
    "Type": {
      "Typo1": "normal",
      "Typo2": "dragon"
    },
    "Egg Distance": "Adventure Sync - 10km",
    "Max CP At Hatch": "1665",
    "Shiny": "si"
  },
  {
    "No.": "#0782",
    "Pic": "https://www.serebii.net/pokemongo/pokemon/782.png",
    "Name": "Jangmo-o",
    "Type": {
      "Typo1": "dragon"
    },
    "Egg Distance": "Adventure Sync - 10km",
    "Max CP At Hatch": "553",
    "Shiny": "si"
  },
  {
    "No.": "#0996",
    "Pic": "https://www.serebii.net/pokemongo/pokemon/996.png",
    "Name": "Frigibax",
    "Type": {
      "Typo1": "dragon",
      "Typo2": "ice"
    },
    "Egg Distance": "10km",
    "Max CP At Hatch": "713",
    "Shiny": "no"
  }
]
